datafi/__init__.py
datafi/dataset.py
datafi-0.0.2.dist-info/WHEEL
datafi-0.0.2.dist-info/METADATA
datafi-0.0.2.dist-info/RECORD
