Metadata-Version: 2.1
Name: datafi
Version: 0.0.2
Summary: Datafi package.
Author-email: Sekhar Ravinutala <sekhar@datafi.us>
Project-URL: Home, https://datafi.us
